odoo/addons/sale_commission_product_based/README.rst
odoo/addons/sale_commission_product_based/__init__.py
odoo/addons/sale_commission_product_based/__manifest__.py
odoo/addons/sale_commission_product_based/i18n/it.po
odoo/addons/sale_commission_product_based/i18n/sale_commission_product_based.pot
odoo/addons/sale_commission_product_based/models/__init__.py
odoo/addons/sale_commission_product_based/models/product_rule.py
odoo/addons/sale_commission_product_based/models/sale_commission.py
odoo/addons/sale_commission_product_based/models/sale_commission_line_mixin.py
odoo/addons/sale_commission_product_based/readme/CONFIGURE.rst
odoo/addons/sale_commission_product_based/readme/CONTRIBUTORS.rst
odoo/addons/sale_commission_product_based/readme/DESCRIPTION.rst
odoo/addons/sale_commission_product_based/readme/USAGE.rst
odoo/addons/sale_commission_product_based/security/ir.model.access.csv
odoo/addons/sale_commission_product_based/static/description/icon.png
odoo/addons/sale_commission_product_based/static/description/index.html
odoo/addons/sale_commission_product_based/tests/__init__.py
odoo/addons/sale_commission_product_based/tests/test_product_fallback.py
odoo/addons/sale_commission_product_based/views/sale_commission_views.xml
odoo12_addon_sale_commission_product_based-12.0.1.0.0.99.dev7.dist-info/METADATA
odoo12_addon_sale_commission_product_based-12.0.1.0.0.99.dev7.dist-info/WHEEL
odoo12_addon_sale_commission_product_based-12.0.1.0.0.99.dev7.dist-info/top_level.txt
odoo12_addon_sale_commission_product_based-12.0.1.0.0.99.dev7.dist-info/RECORD
